rssht_controller_lib/__init__.py
rssht_controller_lib/config.py
rssht_controller_lib/data_access.py
rssht_controller_lib/factories.py
rssht_controller_lib/models.py
rssht_controller_lib/util.py
remote_ssh_tunnel_controller_lib-0.1.0.dist-info/LICENSE
remote_ssh_tunnel_controller_lib-0.1.0.dist-info/METADATA
remote_ssh_tunnel_controller_lib-0.1.0.dist-info/WHEEL
remote_ssh_tunnel_controller_lib-0.1.0.dist-info/top_level.txt
remote_ssh_tunnel_controller_lib-0.1.0.dist-info/RECORD
