Metadata-Version: 2.1
Name: remote-ssh-tunnel-controller-lib
Version: 0.1.0
Summary: Remote SSH Tunnel (RSSHT) controller library
Home-page: https://github.com/guallo/remote-ssh-tunnel-controller-lib
Author: The remote-ssh-tunnel-controller-lib Authors
Author-email: guallo.username@gmail.com
License: UNKNOWN
Platform: UNKNOWN
Classifier: Programming Language :: Python :: 3
Classifier: License :: OSI Approved :: MIT License
Classifier: Operating System :: OS Independent
Requires-Python: >=3.6
Requires-Dist: paramiko (<3,>=2.7.1)
